Metadata-Version: 2.1
Name: django-influxdb-metrics
Version: 1.5.0
Summary: A reusable Django app that sends metrics about your project to InfluxDB
Home-page: https://github.com/bitmazk/django-influxdb-metrics
Author: Martin Brochhaus
Author-email: mbrochh@gmail.com
License: The MIT License
Keywords: django,app,reusable,metrics,influxdb
Platform: OS Independent
Requires-Dist: django (>=1.6)
Requires-Dist: influxdb (>=2.9.1)
Requires-Dist: tld
Requires-Dist: python-server-metrics (>=0.1.9)
